moduleimporter/Importer.py
moduleimporter/PathFinder.py
moduleimporter/__init__.py
moduleimporter/_wrapper.py
moduleimporter/util.py
moduleimporter-1.2.1.dist-info/LICENSE
moduleimporter-1.2.1.dist-info/METADATA
moduleimporter-1.2.1.dist-info/WHEEL
moduleimporter-1.2.1.dist-info/top_level.txt
moduleimporter-1.2.1.dist-info/RECORD
