Metadata-Version: 2.1
Name: moduleimporter
Version: 1.2.1
Summary: Module importer with its own namespace and reflection feature for python.
Home-page: https://github.com/universetraveller/moduleimporter_python
Author: universetraveller
Author-email: universetraveller@outlook.com
License: MIT
Platform: UNKNOWN
Classifier: License :: OSI Approved :: MIT License
Classifier: Programming Language :: Python
Classifier: Programming Language :: Python :: 3
Classifier: Programming Language :: Python :: 3.8
Classifier: Programming Language :: Python :: Implementation :: CPython
Classifier: Topic :: Software Development :: Libraries :: Python Modules
Classifier: Topic :: Utilities
Requires-Python: >=3.8.0
